rqmts/__init__.py
rqmts/__main__.py
rqmts/parsing.py
rqmts-2.0.3.dist-info/LICENSE
rqmts-2.0.3.dist-info/METADATA
rqmts-2.0.3.dist-info/WHEEL
rqmts-2.0.3.dist-info/entry_points.txt
rqmts-2.0.3.dist-info/top_level.txt
rqmts-2.0.3.dist-info/RECORD
