Metadata-Version: 2.1
Name: rqmts
Version: 2.0.3
Summary: Generates pip requirements.txt file for any project by analysing package imports
Home-page: https://github.com/0x48piraj/rqmts
Author: Piyush Raj <0x48piraj>
Author-email: piyush@linuxmail.org
License: BSD-3
Platform: UNKNOWN
Classifier: License :: OSI Approved :: BSD License
Classifier: Programming Language :: Python
Classifier: Programming Language :: Python :: 2
Classifier: Programming Language :: Python :: 3
Classifier: Operating System :: OS Independent
